jinjitsu/__init__.py
jinjitsu/__main__.py
jinjitsu-0.1.1.dist-info/licenses/LICENSE
jinjitsu-0.1.1.dist-info/WHEEL
jinjitsu-0.1.1.dist-info/entry_points.txt
jinjitsu-0.1.1.dist-info/METADATA
jinjitsu-0.1.1.dist-info/RECORD
