Metadata-Version: 2.4
Name: jinjitsu
Version: 0.1.1
Summary: Jinja CLI with all features
Keywords: jinja2,cli,features,include
Author: Vagiz Duseev
Author-email: Vagiz Duseev <vagiz@duseev.com>
License-File: LICENSE
Classifier: Development Status :: 5 - Production/Stable
Classifier: Intended Audience :: Developers
Classifier: License :: OSI Approved :: Apache Software License
Classifier: Programming Language :: Python :: 3
Classifier: Programming Language :: Python :: 3.10
Classifier: Programming Language :: Python :: 3.11
Classifier: Programming Language :: Python :: 3.12
Classifier: Programming Language :: Python :: 3.13
Classifier: Programming Language :: Python :: 3.14
Classifier: Topic :: Software Development :: Code Generators
Classifier: Topic :: Software Development :: Documentation
Classifier: Topic :: Text Processing
Requires-Dist: jinja2>=3.1.6
Maintainer: Vagiz Duseev
Maintainer-email: Vagiz Duseev <vagiz@duseev.com>
Requires-Python: >=3.10
Project-URL: Documentation, https://github.com/vduseev/jinjitsu
Project-URL: Homepage, https://github.com/vduseev/jinjitsu
Project-URL: Issues, https://github.com/vduseev/jinjitsu/issues
Project-URL: Repository, https://github.com/vduseev/jinjitsu
